[{"date":"2023-06-12","leftDaily":{"2023-06-12":1189,"2023-06-13":1379,"2023-06-14":1372,"2023-06-15":1501,"2023-06-16":1482,"2023-06-17":682,"2023-06-18":594,"2023-06-19":1043},"leftCount":9242,"leftTopDomains":{"nytimes.com":548,"independent.co.uk":376,"indiatimes.com":325,"seattletimes.com":283,"thestar.com":273,"latimes.com":261,"newsweek.com":246,"theguardian.com":238,"pressherald.com":153,"cnn.com":148,"bbc.co.uk":140,"rferl.org":130,"theage.com.au":122,"npr.org":120,"rawstory.com":117,"metro.us":115,"channelnewsasia.com":109,"baltimoresun.com":105,"huffpost.com":99,"deadline.com":98,"politicalwire.com":98,"ibtimes.com":97,"alternet.org":88,"variety.com":84,"hollywoodreporter.com":79,"masslive.com":71,"pbs.org":71,"commondreams.org":70,"dw.com":69,"elpais.com":67,"salon.com":65,"voanews.com":65,"thedailybeast.com":64,"dailykos.com":61,"firstpost.com":61,"thegrio.com":61,"theconversation.com":60,"dailyfreeman.com":58,"theatlantic.com":57,"nydailynews.com":54,"mprnews.org":53,"occupydemocrats.com":51,"counterpunch.org":50,"abc.net.au":48,"economist.com":47,"iol.co.za":47,"rollingstone.com":47,"jamaica-gleaner.com":46,"msnbc.com":45,"broadwayworld.com":44,"goodmenproject.com":44,"wusa9.com":44,"newrepublic.com":43,"newyorker.com":43,"time.com":43,"forward.com":42,"politicususa.com":42,"slate.com":42,"aljazeera.com":40,"irishtimes.com":40,"oregonlive.com":40,"jamaicaobserver.com":39,"playbill.com":39,"washingtonblade.com":36,"whyy.org":35,"dailycamera.com":34,"heraldscotland.com":33,"euronews.com":32,"foreignpolicy.com":32,"thenewcivilrightsmovement.com":32,"amny.com":31,"bangkokpost.com":30,"thenation.com":30,"wonkette.com":30,"blackamericaweb.com":29,"lgbtqnation.com":29,"boredpanda.com":28,"news24.com":28,"brooklynvegan.com":27,"dailydot.com":27,"gazettenet.com":27,"huffingtonpost.co.uk":27,"middleeastmonitor.com":27,"vox.com":27,"advocate.com":26,"crooksandliars.com":26,"nbcwashington.com":26,"afro.com":25,"nakedcapitalism.com":25,"phillyvoice.com":25,"boston.com":24,"csmonitor.com":24,"eater.com":24,"essence.com":24,"laist.com":24,"rappler.com":24,"vogue.com":24,"gizmodo.com":23,"queerty.com":23,"rollingout.com":23},"rightDaily":{"2023-06-12":1023,"2023-06-13":1270,"2023-06-14":1106,"2023-06-15":1144,"2023-06-16":1159,"2023-06-17":462,"2023-06-18":454,"2023-06-19":989},"rightCount":7607,"rightTopDomains":{"foxnews.com":378,"krdo.com":280,"washingtontimes.com":266,"dailycaller.com":227,"breitbart.com":191,"bizpacreview.com":172,"news4jax.com":153,"townhall.com":151,"express.co.uk":149,"thesun.co.uk":148,"dennismichaellynch.com":144,"clickorlando.com":142,"thegatewaypundit.com":133,"wnd.com":125,"zerohedge.com":120,"redstate.com":103,"ocregister.com":102,"unionleader.com":102,"whec.com":100,"naturalnews.com":99,"pjmedia.com":91,"click2houston.com":88,"ktar.com":86,"theblaze.com":84,"realclearpolitics.com":81,"stripes.com":81,"kcra.com":78,"hotair.com":75,"wptv.com":70,"wlky.com":68,"wxii12.com":68,"koco.com":65,"wlwt.com":65,"wpbf.com":65,"kmbc.com":64,"wesh.com":64,"thefederalistpapers.org":63,"kjrh.com":62,"kcci.com":61,"nbcdfw.com":61,"wyff4.com":61,"ketv.com":60,"myfox8.com":60,"nysun.com":59,"thefederalist.com":59,"dailylocal.com":58,"globegazette.com":58,"wgal.com":55,"yourerie.com":54,"thenewamerican.com":53,"foxbusiness.com":52,"ijr.com":52,"americanmilitarynews.com":50,"dailysignal.com":49,"wcfcourier.com":49,"freebeacon.com":48,"ksn.com":48,"spectator.org":48,"floridapolitics.com":46,"twitchy.com":46,"wfaa.com":46,"wfla.com":46,"newsbusters.org":44,"rapidcityjournal.com":42,"reason.com":42,"independentsentinel.com":41,"activistpost.com":40,"en-volve.com":38,"greeleytribune.com":38,"lifenews.com":38,"kfor.com":37,"nj1015.com":34,"thepoliticalinsider.com":34,"christianpost.com":33,"frontpagemag.com":33,"journalrecord.com":33,"mrctv.org":33,"americasfreedomfighters.com":31,"gazette.com":31,"rare.us":31,"stream.org":31,"fox8.com":29,"realclearpolicy.com":29,"reporterherald.com":29,"americanthinker.com":28,"charismanews.com":28,"blabbermouth.net":27,"militarytimes.com":27,"oann.com":26,"legalinsurrection.com":25,"israelnationalnews.com":24,"armytimes.com":23,"brobible.com":23,"gopusa.com":23,"ksnt.com":22,"mitchellrepublic.com":21,"keloland.com":20,"joemiller.us":19,"louderwithcrowder.com":19,"marinecorpstimes.com":19},"ratioWeek":1.2149336137767845}]